{"toptags":{"tag":[{"count":100,"name":"Hip-Hop","url":"https://www.last.fm/tag/Hip-Hop"},{"count":74,"name":"rap","url":"https://www.last.fm/tag/rap"},{"count":36,"name":"east coast rap","url":"https://www.last.fm/tag/east+coast+rap"},{"count":24,"name":"hip hop","url":"https://www.last.fm/tag/hip+hop"},{"count":9,"name":"new jersey","url":"https://www.last.fm/tag/new+jersey"},{"count":6,"name":"East Coast","url":"https://www.last.fm/tag/East+Coast"},{"count":2,"name":"hardcore rap","url":"https://www.last.fm/tag/hardcore+rap"},{"count":1,"name":"Redman","url":"https://www.last.fm/tag/Redman"},{"count":1,"name":"wu-tang","url":"https://www.last.fm/tag/wu-tang"},{"count":1,"name":"east coast hip-hop","url":"https://www.last.fm/tag/east+coast+hip-hop"}],"@attr":{"artist":"Redman"}}}