{"album":{"artist":"Redman","mbid":"0ba3de1a-115d-44ec-995a-64f448bd31c9","tags":{"tag":[{"url":"https://www.last.fm/tag/hip-hop","name":"hip-hop"},{"url":"https://www.last.fm/tag/rap","name":"rap"},{"url":"https://www.last.fm/tag/redman","name":"redman"},{"url":"https://www.last.fm/tag/hip+hop","name":"hip hop"},{"url":"https://www.last.fm/tag/1996","name":"1996"}]},"name":"Muddy Waters","image":[{"size":"small","#text":"https://lastfm.freetls.fastly.net/i/u/34s/12af690a2fc905f6cc095d7266bf0efd.jpg"},{"size":"medium","#text":"https://lastfm.freetls.fastly.net/i/u/64s/12af690a2fc905f6cc095d7266bf0efd.jpg"},{"size":"large","#text":"https://lastfm.freetls.fastly.net/i/u/174s/12af690a2fc905f6cc095d7266bf0efd.jpg"},{"size":"extralarge","#text":"https://lastfm.freetls.fastly.net/i/u/300x300/12af690a2fc905f6cc095d7266bf0efd.jpg"},{"size":"mega","#text":"https://lastfm.freetls.fastly.net/i/u/300x300/12af690a2fc905f6cc095d7266bf0efd.jpg"},{"size":"","#text":"https://lastfm.freetls.fastly.net/i/u/300x300/12af690a2fc905f6cc095d7266bf0efd.jpg"}],"tracks":{"track":[{"streamable":{"fulltrack":"0","#text":"0"},"duration":136,"url":"https://www.last.fm/music/Redman/Muddy+Waters/Intro","name":"Intro","@attr":{"rank":1},"artist":{"url":"https://www.last.fm/music/Redman","name":"Redman","mbid":"1f1f6737-b930-46fc-8d25-110bb99f7490"}},{"streamable":{"fulltrack":"0","#text":"0"},"duration":96,"url":"https://www.last.fm/music/Redman/Muddy+Waters/Iz+He+4+Real","name":"Iz He 4 Real","@attr":{"rank":2},"artist":{"url":"https://www.last.fm/music/Redman","name":"Redman","mbid":"1f1f6737-b930-46fc-8d25-110bb99f7490"}},{"streamable":{"fulltrack":"0","#text":"0"},"duration":250,"url":"https://www.last.fm/music/Redman/Muddy+Waters/Rock+Da+Spot","name":"Rock Da Spot","@attr":{"rank":3},"artist":{"url":"https://www.last.fm/music/Redman","name":"Redman","mbid":"1f1f6737-b930-46fc-8d25-110bb99f7490"}},{"streamable":{"fulltrack":"0","#text":"0"},"duration":126,"url":"https://www.last.fm/music/Redman/Muddy+Waters/Welcome+(Interlude)","name":"Welcome (Interlude)","@attr":{"rank":4},"artist":{"url":"https://www.last.fm/music/Redman","name":"Redman","mbid":"1f1f6737-b930-46fc-8d25-110bb99f7490"}},{"streamable":{"fulltrack":"0","#text":"0"},"duration":178,"url":"https://www.last.fm/music/Napalm/Muddy+Waters/Case+Closed","name":"Case Closed","@attr":{"rank":5},"artist":{"url":"https://www.last.fm/music/Napalm","name":"Napalm","mbid":""}},{"streamable":{"fulltrack":"0","#text":"0"},"duration":99,"url":"https://www.last.fm/music/Redman/Muddy+Waters/Pick+It+Up","name":"Pick It Up","@attr":{"rank":6},"artist":{"url":"https://www.last.fm/music/Redman","name":"Redman","mbid":"1f1f6737-b930-46fc-8d25-110bb99f7490"}},{"streamable":{"fulltrack":"0","#text":"0"},"duration":56,"url":"https://www.last.fm/music/Redman/Muddy+Waters/N.I.N.+(Skit)","name":"N.I.N. (Skit)","@attr":{"rank":7},"artist":{"url":"https://www.last.fm/music/Redman","name":"Redman","mbid":"1f1f6737-b930-46fc-8d25-110bb99f7490"}},{"streamable":{"fulltrack":"0","#text":"0"},"duration":154,"url":"https://www.last.fm/music/Redman/Muddy+Waters/Smoke+Buddah","name":"Smoke Buddah","@attr":{"rank":8},"artist":{"url":"https://www.last.fm/music/Redman","name":"Redman","mbid":"1f1f6737-b930-46fc-8d25-110bb99f7490"}},{"streamable":{"fulltrack":"0","#text":"0"},"duration":189,"url":"https://www.last.fm/music/Erick+Sermon/Muddy+Waters/Whateva+Man","name":"Whateva Man","@attr":{"rank":9},"artist":{"url":"https://www.last.fm/music/Erick+Sermon","name":"Erick Sermon","mbid":"7fdb6168-64a8-4b5a-9a6a-e39803e4aec1"}},{"streamable":{"fulltrack":"0","#text":"0"},"duration":77,"url":"https://www.last.fm/music/Redman/Muddy+Waters/Chicken+Head+Convention+(Skit)","name":"Chicken Head Convention (Skit)","@attr":{"rank":10},"artist":{"url":"https://www.last.fm/music/Redman","name":"Redman","mbid":"1f1f6737-b930-46fc-8d25-110bb99f7490"}},{"streamable":{"fulltrack":"0","#text":"0"},"duration":231,"url":"https://www.last.fm/music/Redman/Muddy+Waters/On+Fire","name":"On Fire","@attr":{"rank":11},"artist":{"url":"https://www.last.fm/music/Redman","name":"Redman","mbid":"1f1f6737-b930-46fc-8d25-110bb99f7490"}},{"streamable":{"fulltrack":"0","#text":"0"},"duration":null,"url":"https://www.last.fm/music/Redman/Muddy+Waters/Do+What+Ya+Feel","name":"Do What Ya Feel","@attr":{"rank":12},"artist":{"url":"https://www.last.fm/music/Redman","name":"Redman","mbid":"1f1f6737-b930-46fc-8d25-110bb99f7490"}},{"streamable":{"fulltrack":"0","#text":"0"},"duration":55,"url":"https://www.last.fm/music/Redman/Muddy+Waters/The+Stick+Up+(Skit)","name":"The Stick Up (Skit)","@attr":{"rank":13},"artist":{"url":"https://www.last.fm/music/Redman","name":"Redman","mbid":"1f1f6737-b930-46fc-8d25-110bb99f7490"}},{"streamable":{"fulltrack":"0","#text":"0"},"duration":239,"url":"https://www.last.fm/music/Redman/Muddy+Waters/Creepin%27","name":"Creepin'","@attr":{"rank":14},"artist":{"url":"https://www.last.fm/music/Redman","name":"Redman","mbid":"1f1f6737-b930-46fc-8d25-110bb99f7490"}},{"streamable":{"fulltrack":"0","#text":"0"},"duration":174,"url":"https://www.last.fm/music/K-Solo/Muddy+Waters/It%27s+Like+That+(My+Big+Brother)","name":"It's Like That (My Big Brother)","@attr":{"rank":15},"artist":{"url":"https://www.last.fm/music/K-Solo","name":"K-Solo","mbid":"04b5e4c8-b0ad-4441-8136-08817839a57e"}},{"streamable":{"fulltrack":"0","#text":"0"},"duration":300,"url":"https://www.last.fm/music/Redman/Muddy+Waters/Da+Bump","name":"Da Bump","@attr":{"rank":16},"artist":{"url":"https://www.last.fm/music/Redman","name":"Redman","mbid":"1f1f6737-b930-46fc-8d25-110bb99f7490"}},{"streamable":{"fulltrack":"0","#text":"0"},"duration":58,"url":"https://www.last.fm/music/Redman/Muddy+Waters/Uncle+Quilly+(Skit)","name":"Uncle Quilly (Skit)","@attr":{"rank":17},"artist":{"url":"https://www.last.fm/music/Redman","name":"Redman","mbid":"1f1f6737-b930-46fc-8d25-110bb99f7490"}},{"streamable":{"fulltrack":"0","#text":"0"},"duration":238,"url":"https://www.last.fm/music/Redman/Muddy+Waters/Yesh+Yesh+Ya%27ll","name":"Yesh Yesh Ya'll","@attr":{"rank":18},"artist":{"url":"https://www.last.fm/music/Redman","name":"Redman","mbid":"1f1f6737-b930-46fc-8d25-110bb99f7490"}},{"streamable":{"fulltrack":"0","#text":"0"},"duration":246,"url":"https://www.last.fm/music/Redman/Muddy+Waters/What+U+Lookin%27+4","name":"What U Lookin' 4","@attr":{"rank":19},"artist":{"url":"https://www.last.fm/music/Redman","name":"Redman","mbid":"1f1f6737-b930-46fc-8d25-110bb99f7490"}},{"streamable":{"fulltrack":"0","#text":"0"},"duration":54,"url":"https://www.last.fm/music/Redman/Muddy+Waters/Soopaman+Luva+3+Interview+(Skit)","name":"Soopaman Luva 3 Interview (Skit)","@attr":{"rank":20},"artist":{"url":"https://www.last.fm/music/Redman","name":"Redman","mbid":"1f1f6737-b930-46fc-8d25-110bb99f7490"}},{"streamable":{"fulltrack":"0","#text":"0"},"duration":252,"url":"https://www.last.fm/music/Redman/Muddy+Waters/Soopaman+Luva+3","name":"Soopaman Luva 3","@attr":{"rank":21},"artist":{"url":"https://www.last.fm/music/Redman","name":"Redman","mbid":"1f1f6737-b930-46fc-8d25-110bb99f7490"}},{"streamable":{"fulltrack":"0","#text":"0"},"duration":null,"url":"https://www.last.fm/music/Redman/Muddy+Waters/Rollin%27","name":"Rollin'","@attr":{"rank":22},"artist":{"url":"https://www.last.fm/music/Redman","name":"Redman","mbid":"1f1f6737-b930-46fc-8d25-110bb99f7490"}},{"streamable":{"fulltrack":"0","#text":"0"},"duration":215,"url":"https://www.last.fm/music/Jamal/Muddy+Waters/Da+Ill+Out","name":"Da Ill Out","@attr":{"rank":23},"artist":{"url":"https://www.last.fm/music/Jamal","name":"Jamal","mbid":""}}]},"listeners":"329625","playcount":"2628515","url":"https://www.last.fm/music/Redman/Muddy+Waters"}}