{"track":{"name":"Everybody Everybody (Le Freak Mix)","mbid":"07bb9f3f-b27e-43de-a5ed-6e686ae1bb07","url":"https://www.last.fm/music/Black+Box/_/Everybody+Everybody+(Le+Freak+Mix)","duration":"156000","streamable":{"#text":"0","fulltrack":"0"},"listeners":"17777","playcount":"54201","artist":{"name":"Black Box","mbid":"d73596bb-a8f8-4aae-a323-d881f5245149","url":"https://www.last.fm/music/Black+Box"},"album":{"artist":"Black Box","title":"Hits & Mixes","url":"https://www.last.fm/music/Black+Box/Hits+&+Mixes","image":[{"#text":"https://lastfm.freetls.fastly.net/i/u/34s/ae46262369bef11461d765e3dec4609d.png","size":"small"},{"#text":"https://lastfm.freetls.fastly.net/i/u/64s/ae46262369bef11461d765e3dec4609d.png","size":"medium"},{"#text":"https://lastfm.freetls.fastly.net/i/u/174s/ae46262369bef11461d765e3dec4609d.png","size":"large"},{"#text":"https://lastfm.freetls.fastly.net/i/u/300x300/ae46262369bef11461d765e3dec4609d.png","size":"extralarge"}]},"toptags":{"tag":[]}}}