{"artist":{"name":"Wiley Whitlock","url":"https://www.last.fm/music/Wiley+Whitlock","image":[{"#text":"","size":"small"},{"#text":"","size":"medium"},{"#text":"","size":"large"},{"#text":"","size":"extralarge"},{"#text":"","size":"mega"},{"#text":"","size":""}],"streamable":"0","ontour":"0","stats":{"listeners":"649","playcount":"1352"},"similar":{"artist":[{"name":"Barry Darkley","url":"https://www.last.fm/music/Barry+Darkley","image":[{"#text":"","size":"small"},{"#text":"","size":"medium"},{"#text":"","size":"large"},{"#text":"","size":"extralarge"},{"#text":"","size":"mega"},{"#text":"","size":""}]},{"name":"Greygooz","url":"https://www.last.fm/music/Greygooz","image":[{"#text":"","size":"small"},{"#text":"","size":"medium"},{"#text":"","size":"large"},{"#text":"","size":"extralarge"},{"#text":"","size":"mega"},{"#text":"","size":""}]},{"name":"IshTheKid","url":"https://www.last.fm/music/IshTheKid","image":[{"#text":"","size":"small"},{"#text":"","size":"medium"},{"#text":"","size":"large"},{"#text":"","size":"extralarge"},{"#text":"","size":"mega"},{"#text":"","size":""}]},{"name":"Quantacious","url":"https://www.last.fm/music/Quantacious","image":[{"#text":"https://lastfm.freetls.fastly.net/i/u/34s/2a96cbd8b46e442fc41c2b86b821562f.png","size":"small"},{"#text":"https://lastfm.freetls.fastly.net/i/u/64s/2a96cbd8b46e442fc41c2b86b821562f.png","size":"medium"},{"#text":"https://lastfm.freetls.fastly.net/i/u/174s/2a96cbd8b46e442fc41c2b86b821562f.png","size":"large"},{"#text":"https://lastfm.freetls.fastly.net/i/u/300x300/2a96cbd8b46e442fc41c2b86b821562f.png","size":"extralarge"},{"#text":"https://lastfm.freetls.fastly.net/i/u/300x300/2a96cbd8b46e442fc41c2b86b821562f.png","size":"mega"},{"#text":"https://lastfm.freetls.fastly.net/i/u/300x300/2a96cbd8b46e442fc41c2b86b821562f.png","size":""}]},{"name":"Stacc Styles","url":"https://www.last.fm/music/Stacc+Styles","image":[{"#text":"https://lastfm.freetls.fastly.net/i/u/34s/2a96cbd8b46e442fc41c2b86b821562f.png","size":"small"},{"#text":"https://lastfm.freetls.fastly.net/i/u/64s/2a96cbd8b46e442fc41c2b86b821562f.png","size":"medium"},{"#text":"https://lastfm.freetls.fastly.net/i/u/174s/2a96cbd8b46e442fc41c2b86b821562f.png","size":"large"},{"#text":"https://lastfm.freetls.fastly.net/i/u/300x300/2a96cbd8b46e442fc41c2b86b821562f.png","size":"extralarge"},{"#text":"https://lastfm.freetls.fastly.net/i/u/300x300/2a96cbd8b46e442fc41c2b86b821562f.png","size":"mega"},{"#text":"https://lastfm.freetls.fastly.net/i/u/300x300/2a96cbd8b46e442fc41c2b86b821562f.png","size":""}]}]},"tags":{"tag":[]},"bio":{"links":{"link":{"#text":"","rel":"original","href":"https://last.fm/music/Wiley+Whitlock/+wiki"}},"published":"01 Jan 1970, 00:00","summary":" <a href=\"https://www.last.fm/music/Wiley+Whitlock\">Read more on Last.fm</a>","content":""}}}